adventocr/__init__.py
adventocr/mappings.py
adventocr/parse.py
aocr/__init__.py
aocr/mappings.py
aocr/parse.py
tests/__init__.py
tests/test_parse.py
adventocr-0.1.dist-info/LICENSE
adventocr-0.1.dist-info/METADATA
adventocr-0.1.dist-info/WHEEL
adventocr-0.1.dist-info/top_level.txt
adventocr-0.1.dist-info/RECORD
