Metadata-Version: 2.1
Name: adventocr
Version: 0.1
Summary: Parsing text output for Advent of Code puzzles
Home-page: https://github.com/cqkh42/aoc_letters
Author: cqkh42
Author-email: jackcooper93@gmail.com
License: UNKNOWN
Platform: UNKNOWN
Classifier: Programming Language :: Python :: 3
Classifier: Topic :: Games/Entertainment :: Puzzle Games
